{
    "powers": [
        "duck:modify_swim_speed",
        "duck:long_breath",
        "duck:duck_eyes",
        "origins:aqua_affinity",
        "origins:slow_falling",
        "origins:no_shield",
        "duck:flap",
        "duck:smolman",
        "duck:mean_dog",
        "duck:jump",
        "duck:weaker_body",
        "duck:pescetarian"
    ],
    "icon": {
        "id": "minecraft:yellow_dye"
    },
    "order": 1,
    "impact": 2,
    "name": "Duck",
    "description": "A powerful race that lost it's godlike power a millenia ago, now peaceful, resides in ponds or lakes"
}